<?xml version="1.0" encoding="utf-8"?>
<savedqueries xmlns:xsi="http://www.w3.org/2001/XMLSchema-instance">
  <savedquery>
    <IsCustomizable>1</IsCustomizable>
    <CanBeDeleted>0</CanBeDeleted>
    <isquickfindquery>0</isquickfindquery>
    <isprivate>0</isprivate>
    <isdefault>1</isdefault>
    <savedqueryid>{aecf9668-8922-4746-8ce5-389a9958a0f5}</savedqueryid>
    <layoutxml>
      <grid name="mhcgapps_externalsyncdetails" jump="mhcgapps_syncinternalid" select="1" icon="1" preview="1">
        <row name="mhcgapps_externalsyncdetail" id="mhcgapps_externalsyncdetailid">
          <cell name="mhcgapps_externalsyncsystem" width="100" />
          <cell name="mhcgapps_syncentitytype" width="100" />
          <cell name="mhcgapps_syncinternalid" width="300" />
          <cell name="mhcgapps_syncexternalid" width="273" />
          <cell name="createdon" width="125" />
        </row>
      </grid>
    </layoutxml>
    <querytype>2</querytype>
    <fetchxml>
      <fetch version="1.0" mapping="logical">
        <entity name="mhcgapps_externalsyncdetail">
          <attribute name="mhcgapps_externalsyncdetailid" />
          <attribute name="mhcgapps_syncinternalid" />
          <attribute name="createdon" />
          <filter type="and">
            <condition attribute="statecode" operator="eq" value="0" />
          </filter>
          <attribute name="mhcgapps_syncexternalid" />
          <attribute name="mhcgapps_syncentitytype" />
          <attribute name="mhcgapps_externalsyncsystem" />
          <order attribute="mhcgapps_externalsyncsystem" descending="false" />
          <order attribute="mhcgapps_syncentitytype" descending="false" />
          <order attribute="createdon" descending="false" />
        </entity>
      </fetch>
    </fetchxml>
    <IntroducedVersion>1.0</IntroducedVersion>
    <LocalizedNames>
      <LocalizedName description="External Sync Detail Associated View" languagecode="1033" />
    </LocalizedNames>
  </savedquery>
</savedqueries>